setup.py
excellent/__init__.py
excellent/exceptions.py
excellent.egg-info/PKG-INFO
excellent.egg-info/SOURCES.txt
excellent.egg-info/dependency_links.txt
excellent.egg-info/requires.txt
excellent.egg-info/top_level.txt
excellent/backends/__init__.py
excellent/backends/base.py
excellent/backends/csv_backend.py
excellent/backends/xl_backend.py