Metadata-Version: 1.0
Name: excellent
Version: 0.0.5
Summary: Python library for writing CSV and XLS files
Home-page: http://tech.yipit.com/excellent
Author: Yipit
Author-email: coders@yipit.com
License: UNKNOWN
Platform: UNKNOWN
